{"pid": "01/952", "name": "Ken-ichi Baba", "papers": [{"paper_id": "conf/sc/NozakiNNDBPKATTS06", "year": 2006, "title": "Analytics challenge - Computational oral and speech science on e-science infrastructures", "doi": "10.1145/1188455.1188768", "ee": "https://doi.org/10.1145/1188455.1188768", "authors": [{"pid": "91/929", "name": "Kazunori Nozaki"}, {"pid": "84/5394", "name": "Masaaki Noro"}, {"pid": "92/1482", "name": "Masashi Nakagawa"}, {"pid": "44/2168", "name": "Susumu Date"}, {"pid": "01/952", "name": "Ken-ichi Baba"}, {"pid": "70/2867", "name": "Steven Peltier"}, {"pid": "91/5315", "name": "Toshihiro Kawaguchi"}, {"pid": "81/193", "name": "Toyokazu Akiyama"}, {"pid": "15/1714", "name": "Hiroo Tamagawa"}, {"pid": "79/4127", "name": "Yohsuke Tanaka"}, {"pid": "85/6175", "name": "Shinji Shimojo"}]}], "first_year": 2006, "last_year": 2006, "years_active": 1}