{"pid": "10/2130", "name": "Jim M. Brandt", "papers": [{"paper_id": "conf/sc/SolorzanoSYSBSW24", "year": 2024, "title": "Toward Sustainable HPC: In-Production Deployment of Incentive-Based Power Efficiency Mechanism on the Fugaku Supercomputer", "doi": "10.1109/SC41406.2024.00030", "ee": "https://doi.org/10.1109/SC41406.2024.00030", "authors": [{"pid": "270/5718", "name": "Ana Luisa Veroneze Solórzano"}, {"pid": "71/3069", "name": "Kento Sato"}, {"pid": "84/5244", "name": "Keiji Yamamoto"}, {"pid": "16/9928", "name": "Fumiyoshi Shoji"}, {"pid": "10/2130", "name": "Jim M. Brandt"}, {"pid": "208/0763", "name": "Benjamin Schwaller"}, {"pid": "331/7389", "name": "Sara Petra Walton"}, {"pid": "70/2267", "name": "Jennifer Green"}, {"pid": "76/9083", "name": "Devesh Tiwari"}]}, {"paper_id": "conf/sc/AksarSSALBKEC23", "year": 2023, "title": "Prodigy: Towards Unsupervised Anomaly Detection in Production HPC Systems", "doi": "10.1145/3581784.3607076", "ee": "https://doi.org/10.1145/3581784.3607076", "authors": [{"pid": "245/6255", "name": "Burak Aksar"}, {"pid": "331/7420", "name": "Efe Sencan"}, {"pid": "208/0763", "name": "Benjamin Schwaller"}, {"pid": "170/2069", "name": "Omar Aaziz"}, {"pid": "77/6594", "name": "Vitus J. Leung"}, {"pid": "10/2130", "name": "Jim M. Brandt"}, {"pid": "43/3732", "name": "Brian Kulis"}, {"pid": "27/3108", "name": "Manuel Egele"}, {"pid": "79/3945", "name": "Ayse K. Coskun"}]}, {"paper_id": "conf/sc/CostaPSBT21", "year": 2021, "title": "Systematically inferring I/O performance variability by examining repetitive job behavior", "doi": "10.1145/3458817.3476186", "ee": "https://doi.org/10.1145/3458817.3476186", "authors": [{"pid": "304/5565", "name": "Emily Costa"}, {"pid": "208/1839", "name": "Tirthak Patel"}, {"pid": "208/0763", "name": "Benjamin Schwaller"}, {"pid": "10/2130", "name": "Jim M. Brandt"}, {"pid": "76/9083", "name": "Devesh Tiwari"}]}, {"paper_id": "conf/sc/AgelastosABCEFGMNORSSTT14", "year": 2014, "title": "The Lightweight Distributed Metric Service: A Scalable Infrastructure for Continuous Monitoring of Large Scale Computing Systems and Applications", "doi": "10.1109/SC.2014.18", "ee": "https://doi.org/10.1109/SC.2014.18", "authors": [{"pid": "253/1211", "name": "Anthony M. Agelastos"}, {"pid": "79/414", "name": "Benjamin A. Allan"}, {"pid": "10/2130", "name": "Jim M. Brandt"}, {"pid": "157/2862", "name": "Paul Cassella"}, {"pid": "82/1723", "name": "Jeremy Enos"}, {"pid": "47/9840", "name": "Joshi Fullop"}, {"pid": "59/3993", "name": "Ann C. Gentile"}, {"pid": "157/2819", "name": "Steve Monk"}, {"pid": "03/5987", "name": "Nichamon Naksinehaboon"}, {"pid": "63/9072", "name": "Jeff Ogden"}, {"pid": "33/9072", "name": "Mahesh Rajan"}, {"pid": "50/7892", "name": "Mike Showerman"}, {"pid": "67/7892", "name": "Joel Stevenson"}, {"pid": "84/5279", "name": "Narate Taerat"}, {"pid": "62/2045", "name": "Thomas W. Tucker"}]}], "first_year": 2014, "last_year": 2024, "years_active": 11}