{"pid": "132/7510", "name": "Stephen Taylor McNally", "papers": [{"paper_id": "conf/sc/ZimmerMMAV18", "year": 2018, "title": "GPU age-aware scheduling to improve the reliability of leadership jobs on Titan", "doi": null, "ee": "http://dl.acm.org/citation.cfm?id=3291666", "authors": [{"pid": "12/9032-1", "name": "Christopher Zimmer 0001"}, {"pid": "63/5068", "name": "Don Maxwell"}, {"pid": "132/7510", "name": "Stephen Taylor McNally"}, {"pid": "33/3303", "name": "Scott Atchley"}, {"pid": "v/SudharshanSVazhkudai", "name": "Sudharshan Vazhkudai"}]}], "first_year": 2018, "last_year": 2018, "years_active": 1}