{"pid": "15/4083", "name": "Chi-Chao Chang", "papers": [{"paper_id": "conf/sc/ChangCEK97", "year": 1997, "title": "Evaluating the Performance Limitations of MPMD Communication", "doi": "10.1145/509593.509604", "ee": "https://doi.org/10.1145/509593.509604", "authors": [{"pid": "15/4083", "name": "Chi-Chao Chang"}, {"pid": "81/5635", "name": "Grzegorz Czajkowski"}, {"pid": "76/5208", "name": "Thorsten von Eicken"}, {"pid": "06/4477", "name": "Carl Kesselman"}]}, {"paper_id": "conf/sc/ChangCHE96", "year": 1996, "title": "Low-Latency Communication on the IBM RISC System/6000 SP", "doi": "10.1109/SC.1996.21", "ee": "https://doi.ieeecomputersociety.org/10.1109/SC.1996.21", "authors": [{"pid": "15/4083", "name": "Chi-Chao Chang"}, {"pid": "81/5635", "name": "Grzegorz Czajkowski"}, {"pid": "22/3053", "name": "Chris Hawblitzel"}, {"pid": "76/5208", "name": "Thorsten von Eicken"}]}], "first_year": 1996, "last_year": 1997, "years_active": 2}