{"pid": "180/5118", "name": "Yuanwei Wang", "papers": [{"paper_id": "conf/sc/WangCMYC22", "year": 2022, "title": "Scaling Graph 500 SSSP to 140 Trillion Edges with over 40 Million Cores", "doi": "10.1109/SC41404.2022.00024", "ee": "https://doi.org/10.1109/SC41404.2022.00024", "authors": [{"pid": "180/5118", "name": "Yuanwei Wang"}, {"pid": "214/8159", "name": "Huanqi Cao"}, {"pid": "168/6011", "name": "Zixuan Ma"}, {"pid": "202/6644", "name": "Wanwang Yin"}, {"pid": "60/810", "name": "Wenguang Chen"}]}], "first_year": 2022, "last_year": 2022, "years_active": 1}