{"pid": "20/10102", "name": "Osman Sarood", "papers": [{"paper_id": "conf/sc/SaroodLGK14", "year": 2014, "title": "Maximizing Throughput of Overprovisioned HPC Data Centers Under a Strict Power Budget", "doi": "10.1109/SC.2014.71", "ee": "https://doi.org/10.1109/SC.2014.71", "authors": [{"pid": "20/10102", "name": "Osman Sarood"}, {"pid": "28/8857", "name": "Akhil Langer"}, {"pid": "18/6404-2", "name": "Abhishek Gupta 0002"}, {"pid": "k/LaxmikantVKale", "name": "Laxmikant V. Kalé"}]}, {"paper_id": "conf/sc/SaroodMK13", "year": 2013, "title": "A 'cool' way of improving the reliability of HPC machines", "doi": "10.1145/2503210.2503228", "ee": "https://doi.org/10.1145/2503210.2503228", "authors": [{"pid": "20/10102", "name": "Osman Sarood"}, {"pid": "m/EstebanMeneses", "name": "Esteban Meneses"}, {"pid": "k/LaxmikantVKale", "name": "Laxmikant V. Kalé"}]}, {"paper_id": "conf/sc/SaroodK11", "year": 2011, "title": "A 'cool' load balancer for parallel applications", "doi": "10.1145/2063384.2063412", "ee": "https://doi.org/10.1145/2063384.2063412", "authors": [{"pid": "20/10102", "name": "Osman Sarood"}, {"pid": "k/LaxmikantVKale", "name": "Laxmikant V. Kalé"}]}], "first_year": 2011, "last_year": 2014, "years_active": 4}