{"pid": "311/0486", "name": "Shanghao Liu", "papers": [{"paper_id": "conf/sc/LiuYMLZYLLQ24", "year": 2024, "title": "Moirae: Generating High-Performance Composite Stencil Programs with Global Optimizations", "doi": "10.1109/SC41406.2024.00026", "ee": "https://doi.org/10.1109/SC41406.2024.00026", "authors": [{"pid": "55/2775", "name": "Xiaoyan Liu"}, {"pid": "89/473", "name": "Xinyu Yang"}, {"pid": "33/4801", "name": "Kejie Ma"}, {"pid": "311/0486", "name": "Shanghao Liu"}, {"pid": "211/5802-2", "name": "Kaige Zhang 0002"}, {"pid": "94/8072-2", "name": "Hailong Yang 0002"}, {"pid": "97/4626-13", "name": "Yi Liu 0013"}, {"pid": "26/2404", "name": "Zhongzhi Luan"}, {"pid": "08/4002-2", "name": "Depei Qian 0002"}]}], "first_year": 2024, "last_year": 2024, "years_active": 1}