{"pid": "34/1350", "name": "Hans Vandierendonck", "papers": [{"paper_id": "conf/sc/DAntonioMTV25", "year": 2025, "title": "Wasp: Efficient Asynchronous Single-Source Shortest Path on Multicore Systems via Work Stealing", "doi": "10.1145/3712285.3759872", "ee": "https://doi.org/10.1145/3712285.3759872", "authors": [{"pid": "359/5844", "name": "Marco D'Antonio"}, {"pid": "124/7084", "name": "Son Thai Mai"}, {"pid": "t/PhilippasTsigas", "name": "Philippas Tsigas"}, {"pid": "34/1350", "name": "Hans Vandierendonck"}]}, {"paper_id": "conf/sc/VandierendonckCN13", "year": 2013, "title": "Deterministic scale-free pipeline parallelism with hyperqueues", "doi": "10.1145/2503210.2503233", "ee": "https://doi.org/10.1145/2503210.2503233", "authors": [{"pid": "34/1350", "name": "Hans Vandierendonck"}, {"pid": "136/7931", "name": "Kallia Chronaki"}, {"pid": "50/1235", "name": "Dimitrios S. Nikolopoulos"}]}], "first_year": 2013, "last_year": 2025, "years_active": 13}