{"pid": "421/2341", "name": "Miaoqi Chu", "papers": [{"paper_id": "conf/sc/HuangDUMCLSC25", "year": 2025, "title": "lsCOMP: Efficient Light Source Compression", "doi": "10.1145/3712285.3759814", "ee": "https://doi.org/10.1145/3712285.3759814", "authors": [{"pid": "268/9947", "name": "Yafan Huang"}, {"pid": "76/6449", "name": "Sheng Di"}, {"pid": "178/6201", "name": "Robert Underwood"}, {"pid": "420/4633", "name": "Peco Myint"}, {"pid": "421/2341", "name": "Miaoqi Chu"}, {"pid": "151/4108", "name": "Guanpeng Li"}, {"pid": "29/4139", "name": "Nicholas Schwarz"}, {"pid": "c/FranckCappello", "name": "Franck Cappello"}]}], "first_year": 2025, "last_year": 2025, "years_active": 1}