{"pid": "59/3624", "name": "Uday Bondhugula", "papers": [{"paper_id": "conf/sc/VasistaNBB17", "year": 2017, "title": "Optimizing geometric multigrid method computation using a DSL approach", "doi": "10.1145/3126908.3126968", "ee": "https://doi.org/10.1145/3126908.3126968", "authors": [{"pid": "159/0000", "name": "Vinay Vasista"}, {"pid": "208/1873", "name": "Kumudha Narasimhan"}, {"pid": "208/1904", "name": "Siddharth Bhat"}, {"pid": "59/3624", "name": "Uday Bondhugula"}]}, {"paper_id": "conf/sc/Bondhugula13", "year": 2013, "title": "Compiling affine loop nests for distributed-memory parallel architectures", "doi": "10.1145/2503210.2503289", "ee": "https://doi.org/10.1145/2503210.2503289", "authors": [{"pid": "59/3624", "name": "Uday Bondhugula"}]}, {"paper_id": "conf/sc/BandishtiPB12", "year": 2012, "title": "Tiling stencil computations to maximize parallelism", "doi": "10.1109/SC.2012.107", "ee": "https://doi.org/10.1109/SC.2012.107", "authors": [{"pid": "121/2114", "name": "Vinayaka Bandishti"}, {"pid": "121/2283", "name": "Irshad Pananilath"}, {"pid": "59/3624", "name": "Uday Bondhugula"}]}, {"paper_id": "conf/sc/PouchetBBCRS10", "year": 2010, "title": "Combined Iterative and Model-driven Optimization in an Automatic Parallelization Framework", "doi": "10.1109/SC.2010.14", "ee": "https://doi.org/10.1109/SC.2010.14", "authors": [{"pid": "41/5129", "name": "Louis-Noël Pouchet"}, {"pid": "59/3624", "name": "Uday Bondhugula"}, {"pid": "70/3266", "name": "Cédric Bastoul"}, {"pid": "81/858-1", "name": "Albert Cohen 0001"}, {"pid": "r/JRamanujam", "name": "J. Ramanujam"}, {"pid": "s/PSadayappan", "name": "P. Sadayappan"}]}, {"paper_id": "conf/sc/RenganarayanaBDEO09", "year": 2009, "title": "Compact multi-dimensional kernel extraction for register tiling", "doi": "10.1145/1654059.1654105", "ee": "https://doi.org/10.1145/1654059.1654105", "authors": [{"pid": "68/674", "name": "Lakshminarayanan Renganarayanan"}, {"pid": "59/3624", "name": "Uday Bondhugula"}, {"pid": "11/5810", "name": "Salem Derisavi"}, {"pid": "e/AlexandreEEichenberger", "name": "Alexandre E. Eichenberger"}, {"pid": "o/KevinOBrien", "name": "Kevin O'Brien"}]}], "first_year": 2009, "last_year": 2017, "years_active": 9}