{"pid": "73/3655-3", "name": "Abhinav Agrawal 0003", "papers": [{"paper_id": "conf/sc/AgrawalLT17", "year": 2017, "title": "Leveraging near data processing for high-performance checkpoint/restart", "doi": "10.1145/3126908.3126918", "ee": "https://doi.org/10.1145/3126908.3126918", "authors": [{"pid": "73/3655-3", "name": "Abhinav Agrawal 0003"}, {"pid": "03/2782", "name": "Gabriel H. Loh"}, {"pid": "85/6323", "name": "James Tuck 0001"}]}], "first_year": 2017, "last_year": 2017, "years_active": 1}