{"pid": "76/5208", "name": "Thorsten von Eicken", "papers": [{"paper_id": "conf/sc/ChangCEK97", "year": 1997, "title": "Evaluating the Performance Limitations of MPMD Communication", "doi": "10.1145/509593.509604", "ee": "https://doi.org/10.1145/509593.509604", "authors": [{"pid": "15/4083", "name": "Chi-Chao Chang"}, {"pid": "81/5635", "name": "Grzegorz Czajkowski"}, {"pid": "76/5208", "name": "Thorsten von Eicken"}, {"pid": "06/4477", "name": "Carl Kesselman"}]}, {"paper_id": "conf/sc/ChangCHE96", "year": 1996, "title": "Low-Latency Communication on the IBM RISC System/6000 SP", "doi": "10.1109/SC.1996.21", "ee": "https://doi.ieeecomputersociety.org/10.1109/SC.1996.21", "authors": [{"pid": "15/4083", "name": "Chi-Chao Chang"}, {"pid": "81/5635", "name": "Grzegorz Czajkowski"}, {"pid": "22/3053", "name": "Chris Hawblitzel"}, {"pid": "76/5208", "name": "Thorsten von Eicken"}]}, {"paper_id": "conf/sc/CullerAGKLEY93", "year": 1993, "title": "Parallel programming in Split-C", "doi": "10.1145/169627.169724", "ee": "https://doi.org/10.1145/169627.169724", "authors": [{"pid": "c/DavidECuller", "name": "David E. Culler"}, {"pid": "a/AndreaCArpaciDusseau", "name": "Andrea C. Arpaci-Dusseau"}, {"pid": "g/SCGoldstein", "name": "Seth Copen Goldstein"}, {"pid": "k/AKrishnamurthy", "name": "Arvind Krishnamurthy"}, {"pid": "l/StevenSLumetta", "name": "Steven S. Lumetta"}, {"pid": "76/5208", "name": "Thorsten von Eicken"}, {"pid": "y/KAYelick", "name": "Katherine A. Yelick"}]}], "first_year": 1993, "last_year": 1997, "years_active": 5}