{"pid": "76/5416-3", "name": "Yiming Zhang 0003", "papers": [{"paper_id": "conf/sc/YanQLHCSYCS0025", "year": 2025, "title": "Phoenix: A Refactored I/O Stack for GPU Direct Storage without Phony Buffers", "doi": "10.1145/3712285.3759862", "ee": "https://doi.org/10.1145/3712285.3759862", "authors": [{"pid": "399/1889", "name": "Jianqin Yan"}, {"pid": "97/8988-12", "name": "Shi Qiu 0012"}, {"pid": "249/4229", "name": "Yina Lv"}, {"pid": "92/498", "name": "Yifan Hu"}, {"pid": "175/3324", "name": "Hao Chen"}, {"pid": "20/2488", "name": "Zhirong Shen"}, {"pid": "202/9077", "name": "Xin Yao"}, {"pid": "119/3383", "name": "Renhai Chen"}, {"pid": "60/3690", "name": "Jiwu Shu"}, {"pid": "77/6324-1", "name": "Gong Zhang 0001"}, {"pid": "76/5416-3", "name": "Yiming Zhang 0003"}]}, {"paper_id": "conf/sc/JiaZGLXWL22", "year": 2022, "title": "vGraph: Memory-Efficient Multicore Graph Processing for Traversal-Centric Algorithms", "doi": "10.1109/SC41404.2022.00068", "ee": "https://doi.org/10.1109/SC41404.2022.00068", "authors": [{"pid": "216/9294", "name": "Menghan Jia"}, {"pid": "76/5416-3", "name": "Yiming Zhang 0003"}, {"pid": "36/4875", "name": "Xinbiao Gan"}, {"pid": "254/0830-1", "name": "Dongsheng Li 0001"}, {"pid": "83/10695", "name": "Erci Xu"}, {"pid": "32/7079", "name": "Ruibo Wang"}, {"pid": "31/6932-1", "name": "Kai Lu 0001"}]}], "first_year": 2022, "last_year": 2025, "years_active": 4}