{"pid": "78/4579", "name": "S. Tobita", "papers": [{"paper_id": "conf/sc/ConnerLTIR06", "year": 2006, "title": "Poster reception - Energy/performance modeling for collective communication in 3-D torus cluster networks", "doi": "10.1145/1188455.1188599", "ee": "https://doi.org/10.1145/1188455.1188599", "authors": [{"pid": "03/3362", "name": "S. Conner"}, {"pid": "94/5306", "name": "Greg M. Link"}, {"pid": "78/4579", "name": "S. Tobita"}, {"pid": "i/MaryJaneIrwin", "name": "Mary Jane Irwin"}, {"pid": "96/6134", "name": "Padma Raghavan"}]}], "first_year": 2006, "last_year": 2006, "years_active": 1}