{"pid": "89/5977", "name": "Ioannis Koutis", "papers": [{"paper_id": "conf/sc/BlellochKMT10", "year": 2010, "title": "Hierarchical Diagonal Blocking and Precision Reduction Applied to Combinatorial Multigrid", "doi": "10.1109/SC.2010.29", "ee": "https://doi.org/10.1109/SC.2010.29", "authors": [{"pid": "b/GEBlelloch", "name": "Guy E. Blelloch"}, {"pid": "89/5977", "name": "Ioannis Koutis"}, {"pid": "m/GaryLMiller", "name": "Gary L. Miller"}, {"pid": "64/4316", "name": "Kanat Tangwongsan"}]}], "first_year": 2010, "last_year": 2010, "years_active": 1}