{"pid": "90/2475", "name": "Diego Puppin", "papers": [{"paper_id": "conf/sc/CapanniniBPRP07", "year": 2007, "title": "A job scheduling framework for large computing farms", "doi": "10.1145/1362622.1362695", "ee": "https://doi.org/10.1145/1362622.1362695", "authors": [{"pid": "05/530", "name": "Gabriele Capannini"}, {"pid": "05/907", "name": "Ranieri Baraglia"}, {"pid": "90/2475", "name": "Diego Puppin"}, {"pid": "84/14", "name": "Laura Ricci"}, {"pid": "61/6623", "name": "Marco Pasquali"}]}], "first_year": 2007, "last_year": 2007, "years_active": 1}