{"pid": "93/999", "name": "Jacob Leverich", "papers": [{"paper_id": "conf/sc/AhnJKLS09", "year": 2009, "title": "Future scaling of processor-memory interfaces", "doi": "10.1145/1654059.1654102", "ee": "https://doi.org/10.1145/1654059.1654102", "authors": [{"pid": "a/JungHoAhn", "name": "Jung Ho Ahn"}, {"pid": "j/NormanPJouppi", "name": "Norman P. Jouppi"}, {"pid": "k/ChristoforosEKozyrakis", "name": "Christos Kozyrakis"}, {"pid": "93/999", "name": "Jacob Leverich"}, {"pid": "16/2028", "name": "Robert S. Schreiber"}]}], "first_year": 2009, "last_year": 2009, "years_active": 1}