{"pid": "95/6948", "name": "Fengguang Song", "papers": [{"paper_id": "conf/sc/WangGPTAJS0J0AS25", "year": 2025, "title": "STZ: A High Quality and High Speed Streaming Lossy Compression Framework for Scientific Data", "doi": "10.1145/3712285.3759795", "ee": "https://doi.org/10.1145/3712285.3759795", "authors": [{"pid": "223/2198", "name": "Daoce Wang"}, {"pid": "262/3258", "name": "Pascal Grosset"}, {"pid": "09/8751", "name": "Jesus Pulido"}, {"pid": "234/8464", "name": "Jiannan Tian"}, {"pid": "137/2156", "name": "Tushar M. Athawale"}, {"pid": "390/9604", "name": "Jinda Jia"}, {"pid": "332/1548", "name": "Baixi Sun"}, {"pid": "122/4939-2", "name": "Boyuan Zhang 0002"}, {"pid": "179/2286", "name": "Sian Jin"}, {"pid": "72/2621-8", "name": "Kai Zhao 0008"}, {"pid": "88/2598", "name": "James P. Ahrens"}, {"pid": "95/6948", "name": "Fengguang Song"}]}, {"paper_id": "conf/sc/LiangCTLWLOLSC17", "year": 2017, "title": "Correcting soft errors online in fast fourier transform", "doi": "10.1145/3126908.3126915", "ee": "https://doi.org/10.1145/3126908.3126915", "authors": [{"pid": "31/7475-1", "name": "Xin Liang 0001"}, {"pid": "170/3360", "name": "Jieyang Chen"}, {"pid": "162/0802", "name": "Dingwen Tao"}, {"pid": "184/9149", "name": "Sihuan Li"}, {"pid": "121/1949", "name": "Panruo Wu"}, {"pid": "91/6174-6", "name": "Hongbo Li 0006"}, {"pid": "195/6482", "name": "Kaiming Ouyang"}, {"pid": "208/1828", "name": "Yuanlai Liu"}, {"pid": "95/6948", "name": "Fengguang Song"}, {"pid": "66/5474", "name": "Zizhong Chen"}]}, {"paper_id": "conf/sc/SongLHD10", "year": 2010, "title": "Scalable Tile Communication-Avoiding QR Factorization on Multicore Cluster Systems", "doi": "10.1109/SC.2010.48", "ee": "https://doi.org/10.1109/SC.2010.48", "authors": [{"pid": "95/6948", "name": "Fengguang Song"}, {"pid": "92/397", "name": "Hatem Ltaief"}, {"pid": "53/6634", "name": "Bilel Hadri"}, {"pid": "d/JackDongarra", "name": "Jack J. Dongarra"}]}, {"paper_id": "conf/sc/SongYD09", "year": 2009, "title": "Dynamic task scheduling for linear algebra algorithms on distributed-memory multicore systems", "doi": "10.1145/1654059.1654079", "ee": "https://doi.org/10.1145/1654059.1654079", "authors": [{"pid": "95/6948", "name": "Fengguang Song"}, {"pid": "35/4790", "name": "Asim YarKhan"}, {"pid": "d/JackDongarra", "name": "Jack J. Dongarra"}]}], "first_year": 2009, "last_year": 2025, "years_active": 17}